esrapgra/__init__.py
esrapgra-0.1.1.dist-info/LICENSE
esrapgra-0.1.1.dist-info/METADATA
esrapgra-0.1.1.dist-info/WHEEL
esrapgra-0.1.1.dist-info/top_level.txt
esrapgra-0.1.1.dist-info/RECORD
