Metadata-Version: 2.1
Name: esrapgra
Version: 0.1.1
Summary: The opposite of Argparse
Author-email: Austin Davis-Richardson <hello@agdr.org>
Project-URL: Homepage, https://github.com/audy/esrapgra
Project-URL: Bug Tracker, https://github.com/audy/esrapgra/issues
Classifier: Programming Language :: Python :: 3
Classifier: License :: OSI Approved :: MIT License
Classifier: Operating System :: OS Independent
Requires-Python: >=3.10
License-File: LICENSE
